README.md
setup.cfg
setup.py
cryptomus/Client.py
cryptomus/Payment.py
cryptomus/Payout.py
cryptomus/RequestBuilder.py
cryptomus/RequestExceptions.py
cryptomus/__init__.py
cryptomus.egg-info/PKG-INFO
cryptomus.egg-info/SOURCES.txt
cryptomus.egg-info/dependency_links.txt
cryptomus.egg-info/not-zip-safe
cryptomus.egg-info/top_level.txt