Metadata-Version: 1.0
Name: cryptomus
Version: 1.0.1
Summary: Python SDK for Cryptomus.com API
Home-page: UNKNOWN
Author: UNKNOWN
Author-email: 9or9or9@mail.ru
License: UNKNOWN
Platform: UNKNOWN
